seele_app/__init__.py
seele_app/entrypoint.py
seele_app/settings.py
seele_app/urls.py
seele_app/urls_i18n.py
seele_app/wsgi.py
seele_app/__pycache__/__init__.cpython-310.pyc
seele_app/__pycache__/__init__.cpython-312.pyc
seele_app/__pycache__/settings.cpython-310.pyc
seele_app/__pycache__/settings.cpython-312.pyc
seele_app/__pycache__/urls.cpython-310.pyc
seele_app/__pycache__/urls.cpython-312.pyc
seele_app/__pycache__/urls_i18n.cpython-310.pyc
seele_app/__pycache__/urls_i18n.cpython-312.pyc
seele_app/__pycache__/utils.cpython-310.pyc
seele_app/__pycache__/views.cpython-310.pyc
seele_app/__pycache__/wsgi.cpython-310.pyc
seele_app/__pycache__/wsgi.cpython-312.pyc
website/__init__.py
website/admin.py
website/apps.py
website/models.py
website/tests.py
website/utils.py
website/views.py
website/__pycache__/__init__.cpython-310.pyc
website/__pycache__/__init__.cpython-312.pyc
website/__pycache__/admin.cpython-310.pyc
website/__pycache__/admin.cpython-312.pyc
website/__pycache__/apps.cpython-310.pyc
website/__pycache__/apps.cpython-312.pyc
website/__pycache__/models.cpython-310.pyc
website/__pycache__/models.cpython-312.pyc
website/__pycache__/utils.cpython-310.pyc
website/__pycache__/utils.cpython-312.pyc
website/__pycache__/views.cpython-310.pyc
website/__pycache__/views.cpython-312.pyc
website/locale/jp/LC_MESSAGES/django.mo
website/locale/jp/LC_MESSAGES/django.po
website/migrations/0001_initial.py
website/migrations/__init__.py
website/migrations/__pycache__/0001_initial.cpython-310.pyc
website/migrations/__pycache__/0001_initial.cpython-312.pyc
website/migrations/__pycache__/0002_remove_users_mobile.cpython-310.pyc
website/migrations/__pycache__/0002_remove_users_mobile.cpython-312.pyc
website/migrations/__pycache__/0003_users_location.cpython-310.pyc
website/migrations/__pycache__/0003_users_location.cpython-312.pyc
website/migrations/__pycache__/0004_users_family_size.cpython-310.pyc
website/migrations/__pycache__/0004_users_family_size.cpython-312.pyc
seele_plz-0.0.6.dist-info/LICENSE
seele_plz-0.0.6.dist-info/METADATA
seele_plz-0.0.6.dist-info/WHEEL
seele_plz-0.0.6.dist-info/entry_points.txt
seele_plz-0.0.6.dist-info/top_level.txt
seele_plz-0.0.6.dist-info/RECORD
